LucoPy/ApiCore.py
LucoPy/LucoApi.py
LucoPy/Submissions.py
LucoPy/Utils.py
LucoPy/__init__.py
LucoPy/api_helpers.py
LucoPy/environments.py
LucoPy/exceptions.py
LucoPy/data_quality/__init__.py
LucoPy/data_quality/data_quality.py
LucoPy/data_quality/utils.py
LucoPy/data_quality/great_expectations/__init__.py
LucoPy/data_quality/great_expectations/great_expectations.py
LucoPy/data_quality/great_expectations/utils.py
LucoPy-1.3.14.dist-info/LICENSE
LucoPy-1.3.14.dist-info/METADATA
LucoPy-1.3.14.dist-info/WHEEL
LucoPy-1.3.14.dist-info/top_level.txt
LucoPy-1.3.14.dist-info/RECORD
