Metadata-Version: 2.1
Name: LucoPy
Version: 1.3.14
Summary: Python SDK to support the Luco data observability tool.
Author: Redkite
Author-email: luco.support@redkite.com
License: MIT
Classifier: Programming Language :: Python :: 3
Classifier: License :: OSI Approved :: MIT License
Classifier: Operating System :: OS Independent
Requires-Python: >=3.6
License-File: LICENSE
Requires-Dist: requests
